Func/_init_.py
Func/funciones.py
mh_math_funciones-0.1.2.dist-info/METADATA
mh_math_funciones-0.1.2.dist-info/WHEEL
mh_math_funciones-0.1.2.dist-info/top_level.txt
mh_math_funciones-0.1.2.dist-info/RECORD
