Metadata-Version: 2.4
Name: MH_Math_funciones
Version: 0.1.2
Summary: Librería para los ejercicios 2_3
Author: Marcos Hervás
Requires-Python: >=3.8
